phased_methylation/__init__.py
phased_methylation/call.py
phased_methylation/check_gpu_availability.py
phased_methylation/env.py
phased_methylation/export_bedgraph.py
phased_methylation/export_metilene.py
phased_methylation/gene_body_methylation.py
phased_methylation/intersect.py
phased_methylation/map.py
phased_methylation/mean.py
phased_methylation/merge.py
phased_methylation/methylation_kde.py
phased_methylation/parse_gff.py
phased_methylation/phase.py
phased_methylation/phased_methylation.py
phased_methylation/plot.py
phased_methylation/plot_bedtools.py
phased_methylation/plot_genes.py
phased_methylation/plot_repeats.py
phased_methylation/promoter_methylation.py
phased_methylation/run.py
phased_methylation/split_methyl_bed.py
phased_methylation/tabulate.py
phased_methylation/version.py
phased_methylation/ecoli_example_data/draft.fa
phased_methylation/ecoli_example_data/reads.fasta
phased_methylation/ecoli_example_data/fast5_files/odw_genlab4209_20161213_FN_MN16303_sequencing_run_sample_id_32395_ch107_read4268_strand.fast5
phased_methylation/ecoli_example_data/fast5_files/odw_genlab4209_20161213_FN_MN16303_sequencing_run_sample_id_32395_ch109_read2202_strand.fast5
phased_methylation/ecoli_example_data/fast5_files/odw_genlab4209_20161213_FN_MN16303_sequencing_run_sample_id_32395_ch111_read2109_strand.fast5
phased_methylation/ecoli_example_data/fast5_files/odw_genlab4209_20161213_FN_MN16303_sequencing_run_sample_id_32395_ch111_read5041_strand.fast5
phased_methylation/ecoli_example_data/fast5_files/odw_genlab4209_20161213_FN_MN16303_sequencing_run_sample_id_32395_ch118_read886_strand.fast5
phased_methylation/ecoli_example_data/fast5_files/odw_genlab4209_20161213_FN_MN16303_sequencing_run_sample_id_32395_ch123_read2477_strand.fast5
phased_methylation/ecoli_example_data/fast5_files/odw_genlab4209_20161213_FN_MN16303_sequencing_run_sample_id_32395_ch123_read955_strand.fast5
phased_methylation-0.17.7.dist-info/LICENSE
phased_methylation-0.17.7.dist-info/METADATA
phased_methylation-0.17.7.dist-info/WHEEL
phased_methylation-0.17.7.dist-info/entry_points.txt
phased_methylation-0.17.7.dist-info/top_level.txt
phased_methylation-0.17.7.dist-info/RECORD
