Metadata-Version: 2.1
Name: phased-methylation
Version: 0.17.7
Summary: Pipeline for phased methylation calling on raw nanopore data
Author-email: Anthony Aylward <aaylward@salk.edu>
Project-URL: Homepage, https://gitlab.com/salk-tm/phased-methylation
Project-URL: Documentation, https://salk-tm.gitlab.io/phased-methylation
Classifier: Programming Language :: Python :: 3
Classifier: Operating System :: OS Independent
Classifier: License :: OSI Approved :: MIT License
Requires-Python: >=3.7
License-File: LICENSE
Requires-Dist: cython
Requires-Dist: pandas
Requires-Dist: pysam
Requires-Dist: pybedtools
Requires-Dist: pyfaidx
Requires-Dist: megalodon
Requires-Dist: GPUtil
Requires-Dist: nvsmi
Requires-Dist: psutil
Requires-Dist: tabulate
Requires-Dist: tempfifo
